pyfreefem/__init__.py
pyfreefem/freefemrunner.py
pyfreefem/io.py
pyfreefem/preprocessor.py
pyfreefem/edp/ddm.edp
pyfreefem/edp/io.edp
pyfreefem/examples/__init__.py
pyfreefem/examples/ex00_substitution.py
pyfreefem/examples/ex01_default_set.py
pyfreefem/examples/ex01_default_set_debug.py
pyfreefem/examples/ex02_set_textvar.py
pyfreefem/examples/ex03_ifeq.py
pyfreefem/examples/ex04_for.py
pyfreefem/examples/ex05_magic_comment.py
pyfreefem/examples/ex06_double_backslash.py
pyfreefem/examples/ex07_read_write_FFArray.py
pyfreefem/examples/ex08_read_write_FFMatrix.py
pyfreefem/examples/ex09_freefemrunner_env.py
pyfreefem/examples/ex10_io_export.py
pyfreefem/examples/ex11_io_import.py
pyfreefem/examples/ex12_verbosity_output.py
pyfreefem/examples/ex13_change_cmd.py
pyfreefem/examples/ex14_make_mesh.py
pyfreefem/examples/ex15_laplace.py
pyfreefem/examples/ex16_binary.py
pyfreefem/examples/ex17_read_write_PETScMatrix.py
pyfreefem/examples/ex18_read_write_binaryMatrix.py
pyfreefem/examples/edp/ex1.edp
pyfreefem/examples/edp/ex14.edp
pyfreefem/examples/edp/ex15.edp
pyfreefem/examples/edp/ex2.edp
pyfreefem/examples/edp/ex3.edp
pyfreefem/examples/edp/ex4.edp
pyfreefem/examples/edp/ex5.edp
pyfreefem/examples/edp/ex6.edp
pyfreefem/examples/edp/ex9.edp
pyfreefem/examples/run/io.edp
pyfreefem/examples/run/run.edp
pyfreefem-1.1.5.dist-info/LICENSE
pyfreefem-1.1.5.dist-info/METADATA
pyfreefem-1.1.5.dist-info/WHEEL
pyfreefem-1.1.5.dist-info/top_level.txt
pyfreefem-1.1.5.dist-info/RECORD
