Metadata-Version: 2.1
Name: pyfreefem
Version: 1.1.5
Summary: Package PyFreeFEM for interfacing Python and FreeFEM.
Home-page: https://pyfreefem.readthedocs.io/en/latest/
Author: Florian Feppon
Author-email: florian.feppon@kuleuven.be
License: GNU GPL version 3
Keywords: FreeFEM
Classifier: Programming Language :: Python :: 3
Classifier: License :: OSI Approved :: GNU General Public License v3 (GPLv3)
Classifier: Operating System :: OS Independent
Classifier: Topic :: Scientific/Engineering :: Mathematics
Requires-Python: >=3.6
License-File: LICENSE
Requires-Dist: numpy >=1.12.1
Requires-Dist: scipy >=0.19.1
Requires-Dist: colored >=1.3.93
Requires-Dist: pymedit >=1.2
